SCRIdb/__init__.py
SCRIdb/argsParser.py
SCRIdb/connector.py
SCRIdb/htmlparser.py
SCRIdb/query.py
SCRIdb/sql.py
SCRIdb/submission.py
SCRIdb/tools.py
SCRIdb/transfer.py
SCRIdb/upload_stats.py
SCRIdb/version.py
SCRIdb/worker.py
SCRIdb-1.2.10.data/scripts/create-job
SCRIdb-1.2.10.data/scripts/projectsHTML_index
SCRIdb-1.2.10.data/scripts/scridb
SCRIdb-1.2.10.data/scripts/update_IGOdates
SCRIdb-1.2.10.dist-info/METADATA
SCRIdb-1.2.10.dist-info/WHEEL
SCRIdb-1.2.10.dist-info/top_level.txt
SCRIdb-1.2.10.dist-info/RECORD
