Metadata-Version: 2.1
Name: SCRIdb
Version: 1.2.10
Summary: A platform to handle sequencing data submission and initiation of projects, and to interact with the lab's database - insert meta data, and interactively pull reports and views.
Home-page: https://github.com/dpeerlab/SCRI_db.git
Author: Awni Mousa
Author-email: awnimousa@gmail.com
License: UNKNOWN
Platform: UNKNOWN
Classifier: Programming Language :: Python :: 3
Classifier: License :: OSI Approved :: MIT License
Classifier: Operating System :: OS Independent
Requires-Python: >=3.6
Requires-Dist: bs4
Requires-Dist: mysql-connector-python
Requires-Dist: pandas
Requires-Dist: ipywidgets
Requires-Dist: lxml
Requires-Dist: IPython
Requires-Dist: regex
Requires-Dist: python-dateutil
Requires-Dist: PyYAML
Requires-Dist: tabulate
Requires-Dist: boto3
Requires-Dist: numpy
Requires-Dist: botocore
Requires-Dist: nltk
Requires-Dist: packaging
